{
  "reps": [
    {
      "arm": "worker=0",
      "rep": 1,
      "durationS": 19.95010000002384,
      "rafGapCount": 35,
      "rafGapMaxMs": 783.3,
      "rafStutterCount": 0,
      "longtaskCount": 34,
      "longtaskMaxMs": 745,
      "longtaskTotalMs": 21853,
      "loafCount": 34,
      "loafMaxMs": 772,
      "loafBlockingTotalMs": 20505,
      "heapSlopeMbPerSec": 0.2219886564095926,
      "heapPeakMb": 56.4,
      "heapSampleCount": 6,
      "fireCount": 0
    },
    {
      "arm": "worker=1",
      "rep": 1,
      "durationS": 15.669399999976157,
      "rafGapCount": 25,
      "rafGapMaxMs": 883.3,
      "rafStutterCount": 72,
      "longtaskCount": 18,
      "longtaskMaxMs": 419,
      "longtaskTotalMs": 4024,
      "loafCount": 34,
      "loafMaxMs": 939,
      "loafBlockingTotalMs": 3231,
      "heapSlopeMbPerSec": 0.7210655881552531,
      "heapPeakMb": 57.05,
      "heapSampleCount": 90,
      "fireCount": 2
    },
    {
      "arm": "worker=0",
      "rep": 2,
      "durationS": 19.0535,
      "rafGapCount": 36,
      "rafGapMaxMs": 766.6,
      "rafStutterCount": 0,
      "longtaskCount": 36,
      "longtaskMaxMs": 710,
      "longtaskTotalMs": 22167,
      "loafCount": 36,
      "loafMaxMs": 738,
      "loafBlockingTotalMs": 20734,
      "heapSlopeMbPerSec": 0.16959691223135773,
      "heapPeakMb": 54.85,
      "heapSampleCount": 6,
      "fireCount": 0
    },
    {
      "arm": "worker=1",
      "rep": 2,
      "durationS": 15.028199999928475,
      "rafGapCount": 25,
      "rafGapMaxMs": 1083.3,
      "rafStutterCount": 66,
      "longtaskCount": 15,
      "longtaskMaxMs": 359,
      "longtaskTotalMs": 3501,
      "loafCount": 27,
      "loafMaxMs": 1060,
      "loafBlockingTotalMs": 2566,
      "heapSlopeMbPerSec": 0.6234641485187348,
      "heapPeakMb": 57.39,
      "heapSampleCount": 85,
      "fireCount": 0
    },
    {
      "arm": "worker=0",
      "rep": 3,
      "durationS": 19.9235,
      "rafGapCount": 42,
      "rafGapMaxMs": 1116.7,
      "rafStutterCount": 0,
      "longtaskCount": 42,
      "longtaskMaxMs": 1061,
      "longtaskTotalMs": 23706,
      "loafCount": 42,
      "loafMaxMs": 1104,
      "loafBlockingTotalMs": 22037,
      "heapSlopeMbPerSec": 0.31599394273452414,
      "heapPeakMb": 56.4,
      "heapSampleCount": 7,
      "fireCount": 0
    },
    {
      "arm": "worker=1",
      "rep": 3,
      "durationS": 15.885199999928474,
      "rafGapCount": 24,
      "rafGapMaxMs": 483.3,
      "rafStutterCount": 79,
      "longtaskCount": 20,
      "longtaskMaxMs": 410,
      "longtaskTotalMs": 4207,
      "loafCount": 39,
      "loafMaxMs": 427,
      "loafBlockingTotalMs": 3181,
      "heapSlopeMbPerSec": 0.6475878935537044,
      "heapPeakMb": 59.52,
      "heapSampleCount": 85,
      "fireCount": 3
    },
    {
      "arm": "worker=0",
      "rep": 4,
      "durationS": 18.0095,
      "rafGapCount": 48,
      "rafGapMaxMs": 1199.9,
      "rafStutterCount": 0,
      "longtaskCount": 48,
      "longtaskMaxMs": 1161,
      "longtaskTotalMs": 23183,
      "loafCount": 48,
      "loafMaxMs": 1196,
      "loafBlockingTotalMs": 21291,
      "heapSlopeMbPerSec": 0.19667346606285627,
      "heapPeakMb": 54.86,
      "heapSampleCount": 8,
      "fireCount": 0
    },
    {
      "arm": "worker=1",
      "rep": 4,
      "durationS": 15.644299999952317,
      "rafGapCount": 22,
      "rafGapMaxMs": 1250,
      "rafStutterCount": 72,
      "longtaskCount": 14,
      "longtaskMaxMs": 410,
      "longtaskTotalMs": 2865,
      "loafCount": 28,
      "loafMaxMs": 1270,
      "loafBlockingTotalMs": 2123,
      "heapSlopeMbPerSec": 0.7727820326156858,
      "heapPeakMb": 59.41,
      "heapSampleCount": 97,
      "fireCount": 0
    }
  ],
  "aggA": {
    "rafGapCount": 39,
    "rafGapMaxMs": 950,
    "rafStutterCount": 0,
    "longtaskCount": 39,
    "longtaskMaxMs": 903,
    "longtaskTotalMs": 22675,
    "loafCount": 39,
    "loafMaxMs": 938,
    "loafBlockingTotalMs": 21012.5,
    "heapSlopeMbPerSec": 0.2093310612362244,
    "heapPeakMb": 55.629999999999995,
    "fireCount": 0
  },
  "aggB": {
    "rafGapCount": 24.5,
    "rafGapMaxMs": 983.3,
    "rafStutterCount": 72,
    "longtaskCount": 16.5,
    "longtaskMaxMs": 410,
    "longtaskTotalMs": 3762.5,
    "loafCount": 31,
    "loafMaxMs": 999.5,
    "loafBlockingTotalMs": 2873.5,
    "heapSlopeMbPerSec": 0.6843267408544788,
    "heapPeakMb": 58.4,
    "fireCount": 1
  }
}